softdata/__init__.py
softdata/_core.py
softdata/cleaning.py
softdata/datasets.py
softdata/split.py
softdata/types.py
softdata-0.1.1.dist-info/METADATA
softdata-0.1.1.dist-info/WHEEL
softdata-0.1.1.dist-info/licenses/LICENSE
softdata-0.1.1.dist-info/RECORD
