Metadata-Version: 2.4
Name: softdata
Version: 0.1.1
Summary: Soft Tech Talks: data loading, cleaning, and splitting in 1-3 calls.
Project-URL: Homepage, https://github.com/soft-tech-talks/softdata
Project-URL: Documentation, https://soft-tech-talks.github.io/softdata
Project-URL: Issues, https://github.com/soft-tech-talks/softdata/issues
Author-email: Soft Tech Talks <hello@softtechtalks.org>
License: MIT
License-File: LICENSE
Requires-Python: >=3.9
Requires-Dist: numpy>=1.24
Requires-Dist: pandas>=2.1
Requires-Dist: scikit-learn>=1.3
